fw_gear_mriqc/__init__.py
fw_gear_mriqc/main.py
fw_gear_mriqc/markup.py
fw_gear_mriqc/parser.py
fw_gear_mriqc/setup.py
fw_gear_mriqc/utils.py
fw_gear_mriqc-0.9.0.dist-info/LICENSE
fw_gear_mriqc-0.9.0.dist-info/METADATA
fw_gear_mriqc-0.9.0.dist-info/WHEEL
fw_gear_mriqc-0.9.0.dist-info/RECORD
