Metadata-Version: 2.1
Name: fw-gear-mriqc
Version: 0.9.0
Summary: Image quality metrics for quality assessment of MRI
Home-page: https://gitlab.com/flywheel-io/scientific-solutions/gears/mriqc
License: MIT
Keywords: Flywheel,Gears
Author: Flywheel
Author-email: support@flywheel.io
Requires-Python: >=3.8,<4.0
Classifier: License :: OSI Approved :: MIT License
Classifier: Programming Language :: Python :: 3
Classifier: Programming Language :: Python :: 3.8
Classifier: Programming Language :: Python :: 3.9
Classifier: Programming Language :: Python :: 3.10
Classifier: Programming Language :: Python :: 3.11
Classifier: Programming Language :: Python :: 3.12
Classifier: Topic :: Scientific/Engineering
Requires-Dist: beautifulsoup4 (>=4.12.2,<5.0.0)
Requires-Dist: flywheel-gear-toolkit (>=0.6.10,<0.7.0)
Requires-Dist: flywheel-sdk (>=17.0,<18.0)
Requires-Dist: fw-utils (>=4.3.5,<5.0.0)
Requires-Dist: pyfakefs (>=5.3.0,<6.0.0)
Requires-Dist: pytest-subprocess (>=1.5.0,<2.0.0)
Project-URL: Repository, https://gitlab.com/flywheel-io/scientific-solutions/gears/mriqc
